pykylie/__init__.py
pykylie/__main__.py
pykylie/_version.py
pykylie-1.0.dist-info/METADATA
pykylie-1.0.dist-info/WHEEL
pykylie-1.0.dist-info/licenses/LICENSE
pykylie-1.0.dist-info/RECORD
